Tengxun2019ZhongguoHulianwangQushiBaogao/README.md
Tengxun2019ZhongguoHulianwangQushiBaogao/__init__.py
Tengxun2019ZhongguoHulianwangQushiBaogao/__main__.py
Tengxun2019ZhongguoHulianwangQushiBaogao/file.pdf
Tengxun2019ZhongguoHulianwangQushiBaogao/index.html
tengxun_2019_zhongguo_hulianwang_qushi_baogao-2024.3.5.0.dist-info/METADATA
tengxun_2019_zhongguo_hulianwang_qushi_baogao-2024.3.5.0.dist-info/WHEEL
tengxun_2019_zhongguo_hulianwang_qushi_baogao-2024.3.5.0.dist-info/entry_points.txt
tengxun_2019_zhongguo_hulianwang_qushi_baogao-2024.3.5.0.dist-info/top_level.txt
tengxun_2019_zhongguo_hulianwang_qushi_baogao-2024.3.5.0.dist-info/RECORD
